asciifx/__init__.py
asciifx/__main__.py
asciifx/animator.py
asciifx/event.py
asciifx/perform.py
asciifx/py.typed
asciifx/repl.py
asciifx/util.py
asciifx-0.1.0.dist-info/entry_points.txt
asciifx-0.1.0.dist-info/LICENSE
asciifx-0.1.0.dist-info/WHEEL
asciifx-0.1.0.dist-info/METADATA
asciifx-0.1.0.dist-info/RECORD
