Metadata-Version: 2.1
Name: asciifx
Version: 0.1.0
Summary: Turn Python scripts into seemingly interactive sessions caught on asciicast.
Author-email: Robert Grimm <apparebit@gmail.com>
Requires-Python: >=3.8
Classifier: Environment :: Console
Classifier: License :: OSI Approved :: Apache Software License
Classifier: Operating System :: OS Independent
Classifier: Programming Language :: Python
Classifier: Programming Language :: Python :: 3 :: Only
Classifier: Programming Language :: Python :: 3.8
Classifier: Programming Language :: Python :: 3.9
Classifier: Programming Language :: Python :: 3.10
Classifier: Topic :: Utilities
Requires-Dist: konsole
Requires-Dist: black ; extra == "dev"
Requires-Dist: flit ; extra == "dev"
Requires-Dist: mypy ; extra == "dev"
Project-URL: Home, https://github.com/apparebit/asciifx
Provides-Extra: dev
